RPA_OpenAI.libspec
RPA/OpenAI.py
rpaframework_openai-1.3.3.dist-info/LICENSE
rpaframework_openai-1.3.3.dist-info/METADATA
rpaframework_openai-1.3.3.dist-info/WHEEL
rpaframework_openai-1.3.3.dist-info/RECORD
