Metadata-Version: 2.1
Name: rpaframework-openai
Version: 1.3.3
Summary: OpenAI library for RPA Framework
Home-page: https://rpaframework.org/
License: Apache-2.0
Keywords: robotframework,rpa,automation,openai
Author: RPA Framework
Author-email: rpafw@robocorp.com
Requires-Python: >=3.8,<4.0
Classifier: Development Status :: 5 - Production/Stable
Classifier: Framework :: Robot Framework
Classifier: Framework :: Robot Framework :: Library
Classifier: Intended Audience :: Developers
Classifier: License :: OSI Approved :: Apache Software License
Classifier: Operating System :: OS Independent
Classifier: Programming Language :: Python :: 3
Classifier: Programming Language :: Python :: 3.8
Classifier: Programming Language :: Python :: 3.9
Classifier: Programming Language :: Python :: 3.10
Classifier: Programming Language :: Python :: 3.11
Classifier: Programming Language :: Python :: 3.12
Classifier: Topic :: Software Development :: Libraries
Classifier: Topic :: Software Development :: Libraries :: Python Modules
Requires-Dist: openai (>=0.28.1,<0.29.0)
Project-URL: Documentation, https://rpaframework.org/
Project-URL: Repository, https://github.com/robocorp/rpaframework
